Metadata-Version: 2.4
Name: adafruit-circuitpython-tm1814
Version: 1.0.2
Summary: TM1814 RGB(W) LED driver for RP2 microcontrollers
Author-email: Adafruit Industries <circuitpython@adafruit.com>
License: MIT
Project-URL: Homepage, https://github.com/adafruit/Adafruit_CircuitPython_TM1814
Keywords: adafruit,blinka,circuitpython,micropython,tm1814,rgb,rgbw,neopixel,led,leds,pixelbuf
Classifier: Intended Audience :: Developers
Classifier: Topic :: Software Development :: Libraries
Classifier: Topic :: Software Development :: Embedded Systems
Classifier: Topic :: System :: Hardware
Classifier: License :: OSI Approved :: MIT License
Classifier: Programming Language :: Python :: 3
License-File: LICENSE
Requires-Dist: Adafruit-CircuitPython-pioasm
Requires-Dist: Adafruit-CircuitPython-pixelbuf
Provides-Extra: optional
Dynamic: license-file
